odoo9_addon_account_banking_sepa_credit_transfer-9.0.1.0.0.99.dev40-py3.8-nspkg.pth
odoo_addons/account_banking_sepa_credit_transfer/README.rst
odoo_addons/account_banking_sepa_credit_transfer/__init__.py
odoo_addons/account_banking_sepa_credit_transfer/__openerp__.py
odoo_addons/account_banking_sepa_credit_transfer/post_install.py
odoo_addons/account_banking_sepa_credit_transfer/data/account_payment_method.xml
odoo_addons/account_banking_sepa_credit_transfer/data/pain.001.001.02.xsd
odoo_addons/account_banking_sepa_credit_transfer/data/pain.001.001.03.xsd
odoo_addons/account_banking_sepa_credit_transfer/data/pain.001.001.04.xsd
odoo_addons/account_banking_sepa_credit_transfer/data/pain.001.001.05.xsd
odoo_addons/account_banking_sepa_credit_transfer/data/pain.001.003.03.xsd
odoo_addons/account_banking_sepa_credit_transfer/demo/sepa_credit_transfer_demo.xml
odoo_addons/account_banking_sepa_credit_transfer/i18n/account_banking_sepa_credit_transfer.pot
odoo_addons/account_banking_sepa_credit_transfer/i18n/ca.po
odoo_addons/account_banking_sepa_credit_transfer/i18n/de.po
odoo_addons/account_banking_sepa_credit_transfer/i18n/es.po
odoo_addons/account_banking_sepa_credit_transfer/i18n/fi.po
odoo_addons/account_banking_sepa_credit_transfer/i18n/fr.po
odoo_addons/account_banking_sepa_credit_transfer/i18n/fr_CH.po
odoo_addons/account_banking_sepa_credit_transfer/i18n/it.po
odoo_addons/account_banking_sepa_credit_transfer/i18n/nb_NO.po
odoo_addons/account_banking_sepa_credit_transfer/i18n/nl.po
odoo_addons/account_banking_sepa_credit_transfer/i18n/pt_BR.po
odoo_addons/account_banking_sepa_credit_transfer/i18n/sl.po
odoo_addons/account_banking_sepa_credit_transfer/migrations/9.0.1.0.0/post-migrate.py
odoo_addons/account_banking_sepa_credit_transfer/models/__init__.py
odoo_addons/account_banking_sepa_credit_transfer/models/account_payment_method.py
odoo_addons/account_banking_sepa_credit_transfer/models/account_payment_order.py
odoo9_addon_account_banking_sepa_credit_transfer-9.0.1.0.0.99.dev40.dist-info/METADATA
odoo9_addon_account_banking_sepa_credit_transfer-9.0.1.0.0.99.dev40.dist-info/WHEEL
odoo9_addon_account_banking_sepa_credit_transfer-9.0.1.0.0.99.dev40.dist-info/namespace_packages.txt
odoo9_addon_account_banking_sepa_credit_transfer-9.0.1.0.0.99.dev40.dist-info/top_level.txt
odoo9_addon_account_banking_sepa_credit_transfer-9.0.1.0.0.99.dev40.dist-info/RECORD
