Metadata-Version: 2.1
Name: odoo9-addon-account-banking-sepa-credit-transfer
Version: 9.0.1.0.0.99.dev40
Summary: Create SEPA XML files for Credit Transfers
Home-page: https://github.com/OCA/bank-payment
Author: Akretion, Tecnativa, Odoo Community Association (OCA)
Author-email: support@odoo-community.org
License: AGPL-3
Platform: UNKNOWN
Classifier: Programming Language :: Python
Classifier: Framework :: Odoo
Classifier: License :: OSI Approved :: GNU Affero General Public License v3
Requires-Python: ~=2.7
Requires-Dist: odoo9-addon-account-banking-pain-base
Requires-Dist: odoo (<9.1a,>=9.0a)
